discrete_signals/__init__.py
discrete_signals/signals.py
discrete_signals/test_signals.py
discrete_signals-0.8.2.dist-info/LICENSE
discrete_signals-0.8.2.dist-info/WHEEL
discrete_signals-0.8.2.dist-info/METADATA
discrete_signals-0.8.2.dist-info/RECORD
