Metadata-Version: 2.1
Name: discrete-signals
Version: 0.8.2
Summary: A domain specific language for modeling and manipulating discrete time signals.
Home-page: https://github.com/mvcisback/DiscreteSignals
License: MIT
Author: Marcell Vazquez-Chanlatte
Author-email: mvc@linux.com
Requires-Python: >=3.7,<4.0
Classifier: License :: OSI Approved :: MIT License
Classifier: Programming Language :: Python :: 3
Classifier: Programming Language :: Python :: 3.7
Classifier: Programming Language :: Python :: 3.8
Requires-Dist: attrs (>=19.3.0,<20.0.0)
Requires-Dist: funcy (>=1.14,<2.0)
Requires-Dist: sortedcontainers (>=2.1.0,<3.0.0)
Project-URL: Repository, https://github.com/mvcisback/DiscreteSignals
